{
  "address": "2SeLxJJ2JBXZKeoEqDG9dYYXKEcupjk3bRphiP1p5Ntx",
  "metadata": {
    "name": "journal",
    "version": "0.1.0",
    "spec": "0.1.0",
    "description": "Created with Anchor"
  },
  "instructions": [
    {
      "name": "close",
      "discriminator": [
        98,
        165,
        201,
        177,
        108,
        65,
        206,
        96
      ],
      "accounts": [
        {
          "name": "payer",
          "writable": true,
          "signer": true
        },
        {
          "name": "journal",
          "writable": true
        }
      ],
      "args": []
    },
    {
      "name": "decrement",
      "discriminator": [
        106,
        227,
        168,
        59,
        248,
        27,
        150,
        101
      ],
      "accounts": [
        {
          "name": "journal",
          "writable": true
        }
      ],
      "args": []
    },
    {
      "name": "increment",
      "discriminator": [
        11,
        18,
        104,
        9,
        104,
        174,
        59,
        33
      ],
      "accounts": [
        {
          "name": "journal",
          "writable": true
        }
      ],
      "args": []
    },
    {
      "name": "initialize",
      "discriminator": [
        175,
        175,
        109,
        31,
        13,
        152,
        155,
        237
      ],
      "accounts": [
        {
          "name": "payer",
          "writable": true,
          "signer": true
        },
        {
          "name": "journal",
          "writable": true,
          "signer": true
        },
        {
          "name": "system_program",
          "address": "11111111111111111111111111111111"
        }
      ],
      "args": []
    },
    {
      "name": "set",
      "discriminator": [
        198,
        51,
        53,
        241,
        116,
        29,
        126,
        194
      ],
      "accounts": [
        {
          "name": "journal",
          "writable": true
        }
      ],
      "args": [
        {
          "name": "value",
          "type": "u8"
        }
      ]
    }
  ],
  "accounts": [
    {
      "name": "Journal",
      "discriminator": [
        246,
        141,
        106,
        208,
        98,
        92,
        66,
        208
      ]
    }
  ],
  "types": [
    {
      "name": "Journal",
      "type": {
        "kind": "struct",
        "fields": [
          {
            "name": "count",
            "type": "u8"
          }
        ]
      }
    }
  ]
}